deep_copilot/__init__.py
deep_copilot/audio_tools/__init__.py
deep_copilot/audio_tools/base_audio_tools.py
deep_copilot/audio_tools/vad_tools.py
deep_copilot/command_tools/__init__.py
deep_copilot/command_tools/compat.py
deep_copilot/command_tools/tools.py
deep_copilot/date_tools/__init__.py
deep_copilot/date_tools/datetimeutil.py
deep_copilot/excel_tools/__init__.py
deep_copilot/excel_tools/tools.py
deep_copilot/faiss_tools/__init__.py
deep_copilot/faiss_tools/faiss_tools.py
deep_copilot/hanlp_tools/__init__.py
deep_copilot/hanlp_tools/hanlp_copilot.py
deep_copilot/log_tools/__init__.py
deep_copilot/log_tools/log_tool.py
deep_copilot/misc_tools/__init__.py
deep_copilot/misc_tools/es_tools.py
deep_copilot/misc_tools/tools.py
deep_copilot/mysql_tools/__init__.py
deep_copilot/mysql_tools/mysql_copilot.py
deep_copilot/ocr_tools/__init__.py
deep_copilot/ocr_tools/ocr_tools.py
deep_copilot/ocr_tools/paddle_tools.py
deep_copilot/path_tools/__init__.py
deep_copilot/path_tools/path_copilot.py
deep_copilot/seed_tools/__init__.py
deep_copilot/seed_tools/seed_tool.py
deep_copilot/string_tools/__init__.py
deep_copilot/string_tools/string_copilot.py
deep_copilot/video_and_image_tools/__init__.py
deep_copilot/video_and_image_tools/base_image_tools.py
deep_copilot/video_and_image_tools/base_video_tools.py
deep_copilot/video_and_image_tools/ffmpeg_tools.py
deep_copilot/video_and_image_tools/ffmpyutil.py
deep_copilot/video_and_image_tools/key_frame_extraction_tools.py
deep_copilot/video_and_image_tools/moviepy_tools.py
deep_copilot/video_and_image_tools/multi_epi_opening_rec_tool.py
deep_copilot/video_and_image_tools/opencv_tools.py
deep_copilot/video_and_image_tools/sceneutil.py
deep_copilot/zero_short_model_tools/__init__.py
deep_copilot/zero_short_model_tools/chatgpt_tools.py
deep_copilot/zero_short_model_tools/t5_model_tools.py
deep_copilot-0.0.12.dist-info/LICENSE
deep_copilot-0.0.12.dist-info/METADATA
deep_copilot-0.0.12.dist-info/WHEEL
deep_copilot-0.0.12.dist-info/top_level.txt
deep_copilot-0.0.12.dist-info/RECORD
