Metadata-Version: 2.1
Name: deep-copilot
Version: 0.0.12
Summary: gyw toolkits
Home-page: https://github.com/612twilight/deep_copilot/tree/master/
Author: gyw
Author-email: 240590367@qqq.com
License: Apache Software License 2.0
Keywords: anything not for deep learning
Classifier: Development Status :: 3 - Alpha
Classifier: Intended Audience :: Developers
Classifier: License :: OSI Approved :: Apache Software License
Classifier: Natural Language :: English
Classifier: Programming Language :: Python :: 3.7
Classifier: Programming Language :: Python :: 3.8
Classifier: Programming Language :: Python :: 3.9
Requires-Python: >=3.7
License-File: LICENSE
Requires-Dist: PyMySQL (==1.0.2)
Requires-Dist: tqdm
Requires-Dist: librosa (==0.8.0)
Requires-Dist: matplotlib (==3.5.3)
Requires-Dist: requests
Requires-Dist: scipy (>=1.5.4)
Requires-Dist: pandas (==1.3.5)
Requires-Dist: faiss-cpu (==1.7.2)
Requires-Dist: hanlp (==2.1.0b41)
Requires-Dist: concurrent-log-handler (==0.9.20)
Requires-Dist: elasticsearch (==7.9.1)
Requires-Dist: Pillow (==9.2.0)
Requires-Dist: moviepy (==1.0.3)
Requires-Dist: scenedetect (==0.5.6.1)
Requires-Dist: openai (==0.27.0)
Requires-Dist: transformers (==4.21.3)
Requires-Dist: torch (>=2.0.0)
Requires-Dist: paddlepaddle (==2.3.2)
Requires-Dist: paddleocr (==2.6.1.3)
Requires-Dist: opencv-contrib-python (==4.6.0.66)
